clicks/__init__.py
clicks-0.0.59.dist-info/LICENSE
clicks-0.0.59.dist-info/WHEEL
clicks-0.0.59.dist-info/METADATA
clicks-0.0.59.dist-info/RECORD
