Metadata-Version: 2.1
Name: clicks
Version: 0.0.59
Summary: Tools for a metamodern terminal environment
Home-page: https://ragt.ag/code/clicks
License: AGPL-3.0-or-later
Keywords: CLI,TUI
Author: Angelo Gladding
Author-email: angelo@ragt.ag
Requires-Python: >=3.9,<3.11
Classifier: License :: OSI Approved :: GNU Affero General Public License v3 or later (AGPLv3+)
Classifier: Programming Language :: Python :: 3
Classifier: Programming Language :: Python :: 3.9
Requires-Dist: argcomplete (>=2.0.0,<3.0.0)
Requires-Dist: rich (>=11.2.0,<12.0.0)
Project-URL: Documentation, https://ragt.ag/code/clicks/docs
Project-URL: Repository, https://ragt.ag/code/clicks.git
